[
    {
        "CARI_KOD": "M001",
        "CARI_ISIM": "Örnek Müşteri A.Ş.",
        "BORC_BAKIYESI": 1250.75,
        "ALACAK_BAKIYESI": 0,
        "NET_BAKIYE": 1250.75,
        "GRUP_KODU": "Grup1"
    },
    {
        "CARI_KOD": "M002",
        "CARI_ISIM": "Test Cari Ltd. Şti.",
        "BORC_BAKIYESI": 0,
        "ALACAK_BAKIYESI": 550.0,
        "NET_BAKIYE": -550.0,
        "GRUP_KODU": "Grup2"
    },
    {
        "CARI_KOD": "M003",
        "CARI_ISIM": "Deneme Market",
        "BORC_BAKIYESI": 340.0,
        "ALACAK_BAKIYESI": 100.0,
        "NET_BAKIYE": 240.0,
        "GRUP_KODU": "Grup1"
    }
]